setup.py
PyMarkdownGen/Document.py
PyMarkdownGen/PyMarkdownGen.py
PyMarkdownGen/__init__.py
PyMarkdownGen/version.py
PyMarkdownGen.egg-info/PKG-INFO
PyMarkdownGen.egg-info/SOURCES.txt
PyMarkdownGen.egg-info/dependency_links.txt
PyMarkdownGen.egg-info/not-zip-safe
PyMarkdownGen.egg-info/pbr.json
PyMarkdownGen.egg-info/top_level.txt