Metadata-Version: 1.0
Name: PyMarkdownGen
Version: 0.1.0
Summary: Library to generate markdown formatted text
Home-page: https://github.com/LukasWoodtli/PyMarkdownGen
Author: Lukas Woodtli
Author-email: woodtli.lukas@gmail.com
License: Eclipse Public License - v 1.0
Platform: UNKNOWN
